{
	"info": {
		"_postman_id": "dae1a54a-559e-4e48-9190-1547e3092a6c",
		"name": "ProductService",
		"schema": "https://schema.getpostman.com/json/collection/v2.1.0/collection.json",
		"_exporter_id": "24747203"
	},
	"item": [
		{
			"name": "getProductById",
			"request": {
				"method": "GET",
				"header": [],
				"url": {
					"raw": "http://localhost:8083/product/1",
					"protocol": "http",
					"host": [
						"localhost"
					],
					"port": "8083",
					"path": [
						"product",
						"1"
					]
				}
			},
			"response": []
		},
		{
			"name": "getAllProducts",
			"request": {
				"method": "GET",
				"header": [],
				"url": {
					"raw": "http://localhost:8083/product/",
					"protocol": "http",
					"host": [
						"localhost"
					],
					"port": "8083",
					"path": [
						"product",
						""
					]
				}
			},
			"response": []
		},
		{
			"name": "addProduct",
			"request": {
				"method": "POST",
				"header": [],
				"body": {
					"mode": "raw",
					"raw": "{\n    \"categoryId\": 5,\n    \"inventoryId\": 2,\n    \"name\": \"Chilli\",\n    \"price\": 5,\n    \"quantity\": 1700,\n    \"description\": \"Chilli pepper\"\n}",
					"options": {
						"raw": {
							"language": "json"
						}
					}
				},
				"url": {
					"raw": "http://localhost:8083/product/",
					"protocol": "http",
					"host": [
						"localhost"
					],
					"port": "8083",
					"path": [
						"product",
						""
					]
				}
			},
			"response": []
		},
		{
			"name": "updateProduct",
			"request": {
				"method": "PUT",
				"header": [],
				"body": {
					"mode": "raw",
					"raw": "{\n    \"id\": 1,\n    \"categoryId\": 1,\n    \"inventoryId\": 1,\n    \"name\": \"ToothPaste2\",\n    \"price\": 10,\n    \"quantity\": 100,\n    \"description\": \"Toothpaste2\"\n}",
					"options": {
						"raw": {
							"language": "json"
						}
					}
				},
				"url": {
					"raw": "http://localhost:8083/product/1",
					"protocol": "http",
					"host": [
						"localhost"
					],
					"port": "8083",
					"path": [
						"product",
						"1"
					]
				}
			},
			"response": []
		},
		{
			"name": "updateProductCategory",
			"request": {
				"method": "PUT",
				"header": [],
				"body": {
					"mode": "raw",
					"raw": "{\n    \"categoryId\": 7\n}",
					"options": {
						"raw": {
							"language": "json"
						}
					}
				},
				"url": {
					"raw": "http://localhost:8083/product/category/1",
					"protocol": "http",
					"host": [
						"localhost"
					],
					"port": "8083",
					"path": [
						"product",
						"category",
						"1"
					]
				}
			},
			"response": []
		},
		{
			"name": "getAllInventoryProducts",
			"request": {
				"method": "GET",
				"header": []
			},
			"response": []
		}
	]
}